MANIFEST.in
README.rst
setup.cfg
setup.py
pycircular/__init__.py
pycircular/circular.py
pycircular/plots.py
pycircular/stats.py
pycircular/training.py
pycircular/utils.py
pycircular.egg-info/PKG-INFO
pycircular.egg-info/SOURCES.txt
pycircular.egg-info/dependency_links.txt
pycircular.egg-info/requires.txt
pycircular.egg-info/top_level.txt
pycircular/datasets/__init__.py
pycircular/datasets/base.py
pycircular/datasets/data/transactions.csv.gz