Metadata-Version: 2.1
Name: pycircular
Version: 0.1
Home-page: https://github.com/albahnsen/pycircular
Author: Alejandro Correa Bahnsen
Author-email: al.bahnsen@gmail.com
License: new BSD
Keywords: machine learning,circular,feature engineering
Classifier: Intended Audience :: Science/Research
Classifier: Intended Audience :: Developers
Classifier: Programming Language :: Python
Classifier: Topic :: Software Development
Classifier: Topic :: Scientific/Engineering
Classifier: Programming Language :: Python :: 3
Classifier: Programming Language :: Python :: 3.9
Classifier: Topic :: Scientific/Engineering :: Artificial Intelligence
Classifier: License :: OSI Approved :: BSD License
Classifier: Operating System :: OS Independent
